fastkmeanspp/__init__.py
fastkmeanspp/_kmeans.py
fastkmeanspp/py.typed
fastkmeanspp-0.1.3.dist-info/licenses/LICENSE
fastkmeanspp-0.1.3.dist-info/METADATA
fastkmeanspp-0.1.3.dist-info/WHEEL
fastkmeanspp-0.1.3.dist-info/top_level.txt
fastkmeanspp-0.1.3.dist-info/RECORD
