Metadata-Version: 2.4
Name: fastkmeanspp
Version: 0.1.3
Summary: KMeans++ clustering algorithm
Author: Félix Laplante
Project-URL: Source, https://gitlab.com/felixlaplante0/fastkmeanspp
Classifier: Programming Language :: Python :: 3
Classifier: Operating System :: POSIX :: Linux
Classifier: Operating System :: MacOS
Classifier: Operating System :: Microsoft :: Windows
Requires-Python: >=3.10
License-File: LICENSE
Requires-Dist: numpy
Requires-Dist: scipy
Requires-Dist: scikit-learn
Requires-Dist: faiss-cpu
Dynamic: license-file
